Workbook

Sheet Dashboard
C3: AR / AP Command Center
C5: Executive dashboard for receivables, payables, and expected net cash position
C6: All KPI values update automatically from the AR_Invoices and AP_Invoices tabs.
C8: Total Customers | F8: Total AR Outstanding | I8: Overdue AR | L8: Total Suppliers | O8: Total AP Outstanding | R8: Expected Net Cash
C9: =COUNTIF(Customers!$C$9:$C$208,"<>") | F9: =SUM(AR_Invoices!$K$9:$K$508) | I9: =SUMIFS(AR_Invoices!$K$9:$K$508,AR_Invoices!$N$9:$N$508,"Overdue") | L9: =COUNTIF(Suppliers!$C$9:$C$208,"<>") | O9: =SUM(AP_Invoices!$K$9:$K$508) | R9: =F9-O9
C14: Bucket | D14: Amount | H14: Bucket | I14: Amount | J14: AP Aging | Q14: Status & Controls
C15: Current | D15: =SUMIFS(AR_Invoices!$K$9:$K$508,AR_Invoices!$M$9:$M$508,C15) | H15: Current | I15: =SUMIFS(AP_Invoices!$K$9:$K$508,AP_Invoices!$M$9:$M$508,H15) | Q15: AR Invoices overdue | T15: =COUNTIF(AR_Invoices!$N$9:$N$508,"Overdue")
C16: 30 | D16: =SUMIFS(AR_Invoices!$K$9:$K$508,AR_Invoices!$M$9:$M$508,C16) | H16: 30 | I16: =SUMIFS(AP_Invoices!$K$9:$K$508,AP_Invoices!$M$9:$M$508,H16) | Q16: AP Bills overdue | T16: =COUNTIF(AP_Invoices!$N$9:$N$508,"Overdue")
C17: 60 | D17: =SUMIFS(AR_Invoices!$K$9:$K$508,AR_Invoices!$M$9:$M$508,C17) | H17: 60 | I17: =SUMIFS(AP_Invoices!$K$9:$K$508,AP_Invoices!$M$9:$M$508,H17) | Q17: AR Paid | T17: =SUM(AR_Invoices!$J$9:$J$508)
C18: 90 | D18: =SUMIFS(AR_Invoices!$K$9:$K$508,AR_Invoices!$M$9:$M$508,C18) | H18: 90 | I18: =SUMIFS(AP_Invoices!$K$9:$K$508,AP_Invoices!$M$9:$M$508,H18) | Q18: AP Paid | T18: =SUM(AP_Invoices!$J$9:$J$508)
C19: 90+ | D19: =SUMIFS(AR_Invoices!$K$9:$K$508,AR_Invoices!$M$9:$M$508,C19) | H19: 90+ | I19: =SUMIFS(AP_Invoices!$K$9:$K$508,AP_Invoices!$M$9:$M$508,H19)

Sheet Customers
C3: Customer Master Data
C5: Enter and maintain customer master data
C6: Blue font = manual input; green font = linked values; black font = calculations.
C8: Customer ID | D8: Customer Name | E8: Contact Person | F8: Email | G8: Phone | H8: Country | I8: Credit Limit | J8: Payment Terms | K8: Active? | L8: Notes

Sheet AR_Invoices
C3: Accounts Receivable | AR Invoices
C5: Track customer invoices, payments, overdue balances, and aging
C6: Enter blue cells only. Calculated columns are protected conceptually by black/green font.
C8: Invoice # | D8: Customer ID | E8: Customer Name | F8: Invoice Date | G8: Due Date | H8: Currency | I8: Invoice Amount | J8: Paid Amount | K8: Remaining | L8: Days Past Due | M8: Aging Bucket | N8: Status | O8: Notes
E9: =IFERROR(VLOOKUP(D9,Customers!$C$9:$D$208,2,FALSE),"") | J9: =IF(C9="","",SUMIFS(Payments!$K$9:$K$508,Payments!$E$9:$E$508,"AR",Payments!$F$9:$F$508,C9)) | K9: =IF(I9="","",MAX(0,I9-J9)) | L9: =IF(OR(G9="",I9=""),"",MAX(0,TODAY()-G9)) | M9: =IF(K9="","",IF(K9<=0,"Current",IF(L9<=30,"30",IF(L9<=60,"60",IF(L9<=90,"90","90+"))))) | N9: =IF(K9="","",IF(K9<=0,"Paid",IF(J9<=0,IF(TODAY()>G9,"Overdue","Open"),IF(TODAY()>G9,"Overdue","Partially Paid"))))
E10: =IFERROR(VLOOKUP(D10,Customers!$C$9:$D$208,2,FALSE),"") | J10: =IF(C10="","",SUMIFS(Payments!$K$9:$K$508,Payments!$E$9:$E$508,"AR",Payments!$F$9:$F$508,C10)) | K10: =IF(I10="","",MAX(0,I10-J10)) | L10: =IF(OR(G10="",I10=""),"",MAX(0,TODAY()-G10)) | M10: =IF(K10="","",IF(K10<=0,"Current",IF(L10<=30,"30",IF(L10<=60,"60",IF(L10<=90,"90","90+"))))) | N10: =IF(K10="","",IF(K10<=0,"Paid",IF(J10<=0,IF(TODAY()>G10,"Overdue","Open"),IF(TODAY()>G10,"Overdue","Partially Paid"))))
E11: =IFERROR(VLOOKUP(D11,Customers!$C$9:$D$208,2,FALSE),"") | J11: =IF(C11="","",SUMIFS(Payments!$K$9:$K$508,Payments!$E$9:$E$508,"AR",Payments!$F$9:$F$508,C11)) | K11: =IF(I11="","",MAX(0,I11-J11)) | L11: =IF(OR(G11="",I11=""),"",MAX(0,TODAY()-G11)) | M11: =IF(K11="","",IF(K11<=0,"Current",IF(L11<=30,"30",IF(L11<=60,"60",IF(L11<=90,"90","90+"))))) | N11: =IF(K11="","",IF(K11<=0,"Paid",IF(J11<=0,IF(TODAY()>G11,"Overdue","Open"),IF(TODAY()>G11,"Overdue","Partially Paid"))))
E12: =IFERROR(VLOOKUP(D12,Customers!$C$9:$D$208,2,FALSE),"") | J12: =IF(C12="","",SUMIFS(Payments!$K$9:$K$508,Payments!$E$9:$E$508,"AR",Payments!$F$9:$F$508,C12)) | K12: =IF(I12="","",MAX(0,I12-J12)) | L12: =IF(OR(G12="",I12=""),"",MAX(0,TODAY()-G12)) | M12: =IF(K12="","",IF(K12<=0,"Current",IF(L12<=30,"30",IF(L12<=60,"60",IF(L12<=90,"90","90+"))))) | N12: =IF(K12="","",IF(K12<=0,"Paid",IF(J12<=0,IF(TODAY()>G12,"Overdue","Open"),IF(TODAY()>G12,"Overdue","Partially Paid"))))
E13: =IFERROR(VLOOKUP(D13,Customers!$C$9:$D$208,2,FALSE),"") | J13: =IF(C13="","",SUMIFS(Payments!$K$9:$K$508,Payments!$E$9:$E$508,"AR",Payments!$F$9:$F$508,C13)) | K13: =IF(I13="","",MAX(0,I13-J13)) | L13: =IF(OR(G13="",I13=""),"",MAX(0,TODAY()-G13)) | M13: =IF(K13="","",IF(K13<=0,"Current",IF(L13<=30,"30",IF(L13<=60,"60",IF(L13<=90,"90","90+"))))) | N13: =IF(K13="","",IF(K13<=0,"Paid",IF(J13<=0,IF(TODAY()>G13,"Overdue","Open"),IF(TODAY()>G13,"Overdue","Partially Paid"))))
E14: =IFERROR(VLOOKUP(D14,Customers!$C$9:$D$208,2,FALSE),"") | J14: =IF(C14="","",SUMIFS(Payments!$K$9:$K$508,Payments!$E$9:$E$508,"AR",Payments!$F$9:$F$508,C14)) | K14: =IF(I14="","",MAX(0,I14-J14)) | L14: =IF(OR(G14="",I14=""),"",MAX(0,TODAY()-G14)) | M14: =IF(K14="","",IF(K14<=0,"Current",IF(L14<=30,"30",IF(L14<=60,"60",IF(L14<=90,"90","90+"))))) | N14: =IF(K14="","",IF(K14<=0,"Paid",IF(J14<=0,IF(TODAY()>G14,"Overdue","Open"),IF(TODAY()>G14,"Overdue","Partially Paid"))))
E15: =IFERROR(VLOOKUP(D15,Customers!$C$9:$D$208,2,FALSE),"") | J15: =IF(C15="","",SUMIFS(Payments!$K$9:$K$508,Payments!$E$9:$E$508,"AR",Payments!$F$9:$F$508,C15)) | K15: =IF(I15="","",MAX(0,I15-J15)) | L15: =IF(OR(G15="",I15=""),"",MAX(0,TODAY()-G15)) | M15: =IF(K15="","",IF(K15<=0,"Current",IF(L15<=30,"30",IF(L15<=60,"60",IF(L15<=90,"90","90+"))))) | N15: =IF(K15="","",IF(K15<=0,"Paid",IF(J15<=0,IF(TODAY()>G15,"Overdue","Open"),IF(TODAY()>G15,"Overdue","Partially Paid"))))
E16: =IFERROR(VLOOKUP(D16,Customers!$C$9:$D$208,2,FALSE),"") | J16: =IF(C16="","",SUMIFS(Payments!$K$9:$K$508,Payments!$E$9:$E$508,"AR",Payments!$F$9:$F$508,C16)) | K16: =IF(I16="","",MAX(0,I16-J16)) | L16: =IF(OR(G16="",I16=""),"",MAX(0,TODAY()-G16)) | M16: =IF(K16="","",IF(K16<=0,"Current",IF(L16<=30,"30",IF(L16<=60,"60",IF(L16<=90,"90","90+"))))) | N16: =IF(K16="","",IF(K16<=0,"Paid",IF(J16<=0,IF(TODAY()>G16,"Overdue","Open"),IF(TODAY()>G16,"Overdue","Partially Paid"))))
E17: =IFERROR(VLOOKUP(D17,Customers!$C$9:$D$208,2,FALSE),"") | J17: =IF(C17="","",SUMIFS(Payments!$K$9:$K$508,Payments!$E$9:$E$508,"AR",Payments!$F$9:$F$508,C17)) | K17: =IF(I17="","",MAX(0,I17-J17)) | L17: =IF(OR(G17="",I17=""),"",MAX(0,TODAY()-G17)) | M17: =IF(K17="","",IF(K17<=0,"Current",IF(L17<=30,"30",IF(L17<=60,"60",IF(L17<=90,"90","90+"))))) | N17: =IF(K17="","",IF(K17<=0,"Paid",IF(J17<=0,IF(TODAY()>G17,"Overdue","Open"),IF(TODAY()>G17,"Overdue","Partially Paid"))))
E18: =IFERROR(VLOOKUP(D18,Customers!$C$9:$D$208,2,FALSE),"") | J18: =IF(C18="","",SUMIFS(Payments!$K$9:$K$508,Payments!$E$9:$E$508,"AR",Payments!$F$9:$F$508,C18)) | K18: =IF(I18="","",MAX(0,I18-J18)) | L18: =IF(OR(G18="",I18=""),"",MAX(0,TODAY()-G18)) | M18: =IF(K18="","",IF(K18<=0,"Current",IF(L18<=30,"30",IF(L18<=60,"60",IF(L18<=90,"90","90+"))))) | N18: =IF(K18="","",IF(K18<=0,"Paid",IF(J18<=0,IF(TODAY()>G18,"Overdue","Open"),IF(TODAY()>G18,"Overdue","Partially Paid"))))
E19: =IFERROR(VLOOKUP(D19,Customers!$C$9:$D$208,2,FALSE),"") | J19: =IF(C19="","",SUMIFS(Payments!$K$9:$K$508,Payments!$E$9:$E$508,"AR",Payments!$F$9:$F$508,C19)) | K19: =IF(I19="","",MAX(0,I19-J19)) | L19: =IF(OR(G19="",I19=""),"",MAX(0,TODAY()-G19)) | M19: =IF(K19="","",IF(K19<=0,"Current",IF(L19<=30,"30",IF(L19<=60,"60",IF(L19<=90,"90","90+"))))) | N19: =IF(K19="","",IF(K19<=0,"Paid",IF(J19<=0,IF(TODAY()>G19,"Overdue","Open"),IF(TODAY()>G19,"Overdue","Partially Paid"))))
E20: =IFERROR(VLOOKUP(D20,Customers!$C$9:$D$208,2,FALSE),"") | J20: =IF(C20="","",SUMIFS(Payments!$K$9:$K$508,Payments!$E$9:$E$508,"AR",Payments!$F$9:$F$508,C20)) | K20: =IF(I20="","",MAX(0,I20-J20)) | L20: =IF(OR(G20="",I20=""),"",MAX(0,TODAY()-G20)) | M20: =IF(K20="","",IF(K20<=0,"Current",IF(L20<=30,"30",IF(L20<=60,"60",IF(L20<=90,"90","90+"))))) | N20: =IF(K20="","",IF(K20<=0,"Paid",IF(J20<=0,IF(TODAY()>G20,"Overdue","Open"),IF(TODAY()>G20,"Overdue","Partially Paid"))))
... E508: =IFERROR(VLOOKUP(D508,Customers!$C$9:$D$208,2,FALSE),"") | J508: =IF(C508="","",SUMIFS(Payments!$K$9:$K$508,Payments!$E$9:$E$508,"AR",Payments!$F$9:$F$508,C508)) | K508: =IF(I508="","",MAX(0,I508-J508)) | L508: =IF(OR(G508="",I508=""),"",MAX(0,TODAY()-G508)) | M508: =IF(K508="","",IF(K508<=0,"Current",IF(L508<=30,"30",IF(L508<=60,"60",IF(L508<=90,"90","90+"))))) | N508: =IF(K508="","",IF(K508<=0,"Paid",IF(J508<=0,IF(TODAY()>G508,"Overdue","Open"),IF(TODAY()>G508,"Overdue","Partially Paid"))))

Sheet Suppliers
C3: Supplier Master Data
C5: Enter and maintain supplier master data
C6: Blue font = manual input; keep supplier IDs unique.
C8: Supplier ID | D8: Supplier Name | E8: Contact Person | F8: Email | G8: Phone | H8: Country | I8: Credit Terms | J8: Active? | K8: Notes

Sheet AP_Invoices
C3: Accounts Payable | AP Bills
C5: Track supplier bills, payment dates, overdue balances, and aging
C6: Enter blue cells only. Calculated columns update automatically.
C8: Bill # | D8: Supplier ID | E8: Supplier Name | F8: Bill Date | G8: Due Date | H8: Currency | I8: Bill Amount | J8: Paid Amount | K8: Remaining | L8: Days Past Due | M8: Aging Bucket | N8: Status | O8: Notes
E9: =IFERROR(VLOOKUP(D9,Suppliers!$C$9:$D$208,2,FALSE),"") | J9: =IF(C9="","",SUMIFS(Payments!$K$9:$K$508,Payments!$E$9:$E$508,"AP",Payments!$F$9:$F$508,C9)) | K9: =IF(I9="","",MAX(0,I9-J9)) | L9: =IF(OR(G9="",I9=""),"",MAX(0,TODAY()-G9)) | M9: =IF(K9="","",IF(K9<=0,"Current",IF(L9<=30,"30",IF(L9<=60,"60",IF(L9<=90,"90","90+"))))) | N9: =IF(K9="","",IF(K9<=0,"Paid",IF(J9<=0,IF(TODAY()>G9,"Overdue","Open"),IF(TODAY()>G9,"Overdue","Partially Paid"))))
E10: =IFERROR(VLOOKUP(D10,Suppliers!$C$9:$D$208,2,FALSE),"") | J10: =IF(C10="","",SUMIFS(Payments!$K$9:$K$508,Payments!$E$9:$E$508,"AP",Payments!$F$9:$F$508,C10)) | K10: =IF(I10="","",MAX(0,I10-J10)) | L10: =IF(OR(G10="",I10=""),"",MAX(0,TODAY()-G10)) | M10: =IF(K10="","",IF(K10<=0,"Current",IF(L10<=30,"30",IF(L10<=60,"60",IF(L10<=90,"90","90+"))))) | N10: =IF(K10="","",IF(K10<=0,"Paid",IF(J10<=0,IF(TODAY()>G10,"Overdue","Open"),IF(TODAY()>G10,"Overdue","Partially Paid"))))
E11: =IFERROR(VLOOKUP(D11,Suppliers!$C$9:$D$208,2,FALSE),"") | J11: =IF(C11="","",SUMIFS(Payments!$K$9:$K$508,Payments!$E$9:$E$508,"AP",Payments!$F$9:$F$508,C11)) | K11: =IF(I11="","",MAX(0,I11-J11)) | L11: =IF(OR(G11="",I11=""),"",MAX(0,TODAY()-G11)) | M11: =IF(K11="","",IF(K11<=0,"Current",IF(L11<=30,"30",IF(L11<=60,"60",IF(L11<=90,"90","90+"))))) | N11: =IF(K11="","",IF(K11<=0,"Paid",IF(J11<=0,IF(TODAY()>G11,"Overdue","Open"),IF(TODAY()>G11,"Overdue","Partially Paid"))))
E12: =IFERROR(VLOOKUP(D12,Suppliers!$C$9:$D$208,2,FALSE),"") | J12: =IF(C12="","",SUMIFS(Payments!$K$9:$K$508,Payments!$E$9:$E$508,"AP",Payments!$F$9:$F$508,C12)) | K12: =IF(I12="","",MAX(0,I12-J12)) | L12: =IF(OR(G12="",I12=""),"",MAX(0,TODAY()-G12)) | M12: =IF(K12="","",IF(K12<=0,"Current",IF(L12<=30,"30",IF(L12<=60,"60",IF(L12<=90,"90","90+"))))) | N12: =IF(K12="","",IF(K12<=0,"Paid",IF(J12<=0,IF(TODAY()>G12,"Overdue","Open"),IF(TODAY()>G12,"Overdue","Partially Paid"))))
E13: =IFERROR(VLOOKUP(D13,Suppliers!$C$9:$D$208,2,FALSE),"") | J13: =IF(C13="","",SUMIFS(Payments!$K$9:$K$508,Payments!$E$9:$E$508,"AP",Payments!$F$9:$F$508,C13)) | K13: =IF(I13="","",MAX(0,I13-J13)) | L13: =IF(OR(G13="",I13=""),"",MAX(0,TODAY()-G13)) | M13: =IF(K13="","",IF(K13<=0,"Current",IF(L13<=30,"30",IF(L13<=60,"60",IF(L13<=90,"90","90+"))))) | N13: =IF(K13="","",IF(K13<=0,"Paid",IF(J13<=0,IF(TODAY()>G13,"Overdue","Open"),IF(TODAY()>G13,"Overdue","Partially Paid"))))
E14: =IFERROR(VLOOKUP(D14,Suppliers!$C$9:$D$208,2,FALSE),"") | J14: =IF(C14="","",SUMIFS(Payments!$K$9:$K$508,Payments!$E$9:$E$508,"AP",Payments!$F$9:$F$508,C14)) | K14: =IF(I14="","",MAX(0,I14-J14)) | L14: =IF(OR(G14="",I14=""),"",MAX(0,TODAY()-G14)) | M14: =IF(K14="","",IF(K14<=0,"Current",IF(L14<=30,"30",IF(L14<=60,"60",IF(L14<=90,"90","90+"))))) | N14: =IF(K14="","",IF(K14<=0,"Paid",IF(J14<=0,IF(TODAY()>G14,"Overdue","Open"),IF(TODAY()>G14,"Overdue","Partially Paid"))))
E15: =IFERROR(VLOOKUP(D15,Suppliers!$C$9:$D$208,2,FALSE),"") | J15: =IF(C15="","",SUMIFS(Payments!$K$9:$K$508,Payments!$E$9:$E$508,"AP",Payments!$F$9:$F$508,C15)) | K15: =IF(I15="","",MAX(0,I15-J15)) | L15: =IF(OR(G15="",I15=""),"",MAX(0,TODAY()-G15)) | M15: =IF(K15="","",IF(K15<=0,"Current",IF(L15<=30,"30",IF(L15<=60,"60",IF(L15<=90,"90","90+"))))) | N15: =IF(K15="","",IF(K15<=0,"Paid",IF(J15<=0,IF(TODAY()>G15,"Overdue","Open"),IF(TODAY()>G15,"Overdue","Partially Paid"))))
E16: =IFERROR(VLOOKUP(D16,Suppliers!$C$9:$D$208,2,FALSE),"") | J16: =IF(C16="","",SUMIFS(Payments!$K$9:$K$508,Payments!$E$9:$E$508,"AP",Payments!$F$9:$F$508,C16)) | K16: =IF(I16="","",MAX(0,I16-J16)) | L16: =IF(OR(G16="",I16=""),"",MAX(0,TODAY()-G16)) | M16: =IF(K16="","",IF(K16<=0,"Current",IF(L16<=30,"30",IF(L16<=60,"60",IF(L16<=90,"90","90+"))))) | N16: =IF(K16="","",IF(K16<=0,"Paid",IF(J16<=0,IF(TODAY()>G16,"Overdue","Open"),IF(TODAY()>G16,"Overdue","Partially Paid"))))
E17: =IFERROR(VLOOKUP(D17,Suppliers!$C$9:$D$208,2,FALSE),"") | J17: =IF(C17="","",SUMIFS(Payments!$K$9:$K$508,Payments!$E$9:$E$508,"AP",Payments!$F$9:$F$508,C17)) | K17: =IF(I17="","",MAX(0,I17-J17)) | L17: =IF(OR(G17="",I17=""),"",MAX(0,TODAY()-G17)) | M17: =IF(K17="","",IF(K17<=0,"Current",IF(L17<=30,"30",IF(L17<=60,"60",IF(L17<=90,"90","90+"))))) | N17: =IF(K17="","",IF(K17<=0,"Paid",IF(J17<=0,IF(TODAY()>G17,"Overdue","Open"),IF(TODAY()>G17,"Overdue","Partially Paid"))))
E18: =IFERROR(VLOOKUP(D18,Suppliers!$C$9:$D$208,2,FALSE),"") | J18: =IF(C18="","",SUMIFS(Payments!$K$9:$K$508,Payments!$E$9:$E$508,"AP",Payments!$F$9:$F$508,C18)) | K18: =IF(I18="","",MAX(0,I18-J18)) | L18: =IF(OR(G18="",I18=""),"",MAX(0,TODAY()-G18)) | M18: =IF(K18="","",IF(K18<=0,"Current",IF(L18<=30,"30",IF(L18<=60,"60",IF(L18<=90,"90","90+"))))) | N18: =IF(K18="","",IF(K18<=0,"Paid",IF(J18<=0,IF(TODAY()>G18,"Overdue","Open"),IF(TODAY()>G18,"Overdue","Partially Paid"))))
E19: =IFERROR(VLOOKUP(D19,Suppliers!$C$9:$D$208,2,FALSE),"") | J19: =IF(C19="","",SUMIFS(Payments!$K$9:$K$508,Payments!$E$9:$E$508,"AP",Payments!$F$9:$F$508,C19)) | K19: =IF(I19="","",MAX(0,I19-J19)) | L19: =IF(OR(G19="",I19=""),"",MAX(0,TODAY()-G19)) | M19: =IF(K19="","",IF(K19<=0,"Current",IF(L19<=30,"30",IF(L19<=60,"60",IF(L19<=90,"90","90+"))))) | N19: =IF(K19="","",IF(K19<=0,"Paid",IF(J19<=0,IF(TODAY()>G19,"Overdue","Open"),IF(TODAY()>G19,"Overdue","Partially Paid"))))
E20: =IFERROR(VLOOKUP(D20,Suppliers!$C$9:$D$208,2,FALSE),"") | J20: =IF(C20="","",SUMIFS(Payments!$K$9:$K$508,Payments!$E$9:$E$508,"AP",Payments!$F$9:$F$508,C20)) | K20: =IF(I20="","",MAX(0,I20-J20)) | L20: =IF(OR(G20="",I20=""),"",MAX(0,TODAY()-G20)) | M20: =IF(K20="","",IF(K20<=0,"Current",IF(L20<=30,"30",IF(L20<=60,"60",IF(L20<=90,"90","90+"))))) | N20: =IF(K20="","",IF(K20<=0,"Paid",IF(J20<=0,IF(TODAY()>G20,"Overdue","Open"),IF(TODAY()>G20,"Overdue","Partially Paid"))))
... E508: =IFERROR(VLOOKUP(D508,Suppliers!$C$9:$D$208,2,FALSE),"") | J508: =IF(C508="","",SUMIFS(Payments!$K$9:$K$508,Payments!$E$9:$E$508,"AP",Payments!$F$9:$F$508,C508)) | K508: =IF(I508="","",MAX(0,I508-J508)) | L508: =IF(OR(G508="",I508=""),"",MAX(0,TODAY()-G508)) | M508: =IF(K508="","",IF(K508<=0,"Current",IF(L508<=30,"30",IF(L508<=60,"60",IF(L508<=90,"90","90+"))))) | N508: =IF(K508="","",IF(K508<=0,"Paid",IF(J508<=0,IF(TODAY()>G508,"Overdue","Open"),IF(TODAY()>G508,"Overdue","Partially Paid"))))

Sheet Lists
C3: Lists & Controls
C5: Dropdown values used throughout the workbook
C6: Maintain lists here if you want to customize statuses or payment terms.
C8: Payment Status | D8: Currency | E8: Payment Terms
C9: Open | D9: USD | E9: Due on receipt
C10: Paid | D10: EUR | E10: 7 days
C11: Partially Paid | D11: GBP | E11: 15 days
C12: Overdue | D12: SAR | E12: 30 days
D13: AED | E13: 45 days
D14: EGP | E14: 60 days
D15: Other | E15: 90 days

Sheet Read_Me
C3: Read Me | User Guide
C5: How to use this AR/AP template
C6: Use this short guide before entering data.
C8: Purpose | D8: Centralized tracking of customers, suppliers, invoices/bills, payments, outstanding balances, overdue items, and aging.
C10: Workflow | D10: 1) Add customers and suppliers. 2) Enter invoices/bills in AR_Invoices and AP_Invoices. 3) Record every receipt/payment in Payments; the Paid Amount and Remaining columns update automatically. 4) Review Dashboard.
C12: Aging logic | D12: A document is Current when it is not past due. Aging is based on TODAY() minus Due Date and uses Current / 30 / 60 / 90 / 90+ buckets.
C14: Overdue logic | D14: An item is Overdue when its Remaining balance is positive and TODAY() is after the Due Date. Fully paid items are marked Paid.
C16: Color convention | D16: Blue text = manual input. Black text = calculation on the same sheet. Green text = link or formula referencing another sheet.
C18: Important | D18: Enter dates as real Excel dates. Keep Customer ID, Supplier ID, Invoice #, Bill #, and Payment ID unique. Do not overwrite calculated columns. Currency is shown as a neutral amount format; use one consistent currency per reporting view.

Sheet Payments
C3: Payments Register
C5: Enter every customer receipt and supplier payment here
C6: Type AR = customer receipt; Type AP = supplier payment. Paid Amount in AR/AP updates automatically from this register.
C8: Payment ID | D8: Payment Date | E8: Type | F8: Document # | G8: Counterparty ID | H8: Counterparty Name | I8: Currency | J8: Method | K8: Amount | L8: Reference | M8: Notes
H9: =IF(F9="","",IF(E9="AR",IFERROR(VLOOKUP(G9,Customers!$C$9:$D$208,2,FALSE),""),IFERROR(VLOOKUP(G9,Suppliers!$C$9:$D$208,2,FALSE),"")))
H10: =IF(F10="","",IF(E10="AR",IFERROR(VLOOKUP(G10,Customers!$C$9:$D$208,2,FALSE),""),IFERROR(VLOOKUP(G10,Suppliers!$C$9:$D$208,2,FALSE),"")))
H11: =IF(F11="","",IF(E11="AR",IFERROR(VLOOKUP(G11,Customers!$C$9:$D$208,2,FALSE),""),IFERROR(VLOOKUP(G11,Suppliers!$C$9:$D$208,2,FALSE),"")))
H12: =IF(F12="","",IF(E12="AR",IFERROR(VLOOKUP(G12,Customers!$C$9:$D$208,2,FALSE),""),IFERROR(VLOOKUP(G12,Suppliers!$C$9:$D$208,2,FALSE),"")))
H13: =IF(F13="","",IF(E13="AR",IFERROR(VLOOKUP(G13,Customers!$C$9:$D$208,2,FALSE),""),IFERROR(VLOOKUP(G13,Suppliers!$C$9:$D$208,2,FALSE),"")))
H14: =IF(F14="","",IF(E14="AR",IFERROR(VLOOKUP(G14,Customers!$C$9:$D$208,2,FALSE),""),IFERROR(VLOOKUP(G14,Suppliers!$C$9:$D$208,2,FALSE),"")))
H15: =IF(F15="","",IF(E15="AR",IFERROR(VLOOKUP(G15,Customers!$C$9:$D$208,2,FALSE),""),IFERROR(VLOOKUP(G15,Suppliers!$C$9:$D$208,2,FALSE),"")))
H16: =IF(F16="","",IF(E16="AR",IFERROR(VLOOKUP(G16,Customers!$C$9:$D$208,2,FALSE),""),IFERROR(VLOOKUP(G16,Suppliers!$C$9:$D$208,2,FALSE),"")))
H17: =IF(F17="","",IF(E17="AR",IFERROR(VLOOKUP(G17,Customers!$C$9:$D$208,2,FALSE),""),IFERROR(VLOOKUP(G17,Suppliers!$C$9:$D$208,2,FALSE),"")))
H18: =IF(F18="","",IF(E18="AR",IFERROR(VLOOKUP(G18,Customers!$C$9:$D$208,2,FALSE),""),IFERROR(VLOOKUP(G18,Suppliers!$C$9:$D$208,2,FALSE),"")))
H19: =IF(F19="","",IF(E19="AR",IFERROR(VLOOKUP(G19,Customers!$C$9:$D$208,2,FALSE),""),IFERROR(VLOOKUP(G19,Suppliers!$C$9:$D$208,2,FALSE),"")))
H20: =IF(F20="","",IF(E20="AR",IFERROR(VLOOKUP(G20,Customers!$C$9:$D$208,2,FALSE),""),IFERROR(VLOOKUP(G20,Suppliers!$C$9:$D$208,2,FALSE),"")))
... H508: =IF(F508="","",IF(E508="AR",IFERROR(VLOOKUP(G508,Customers!$C$9:$D$208,2,FALSE),""),IFERROR(VLOOKUP(G508,Suppliers!$C$9:$D$208,2,FALSE),"")))
